[[], [{"key": "3", "label": "2 BHK", "propertyTypeName": "Apartment", "propertyTypeId": 1, "range": null, "data": [{"id": "885727", "price": {"value": null, "displayValue": "Price on Request", "unit": null, "deposit": null, "description": null}, "unitsAvailable": null, "areaConfig": [{"name": "Saleable Area", "areaInfo": {"value": 1100, "unit": "sq.ft", "displayArea": "1100.00"}}], "emi": null, "averagePrice": "Price on request", "floorPlan": null, "projectAttributes": null, "features": null, "additionalFields": [{"id": "bedroom", "value": "2", "label": "Bedroom"}]}]}, {"key": "4", "label": "3 BHK", "propertyTypeName": "Apartment", "propertyTypeId": 1, "range": null, "data": [{"id": "885728", "price": {"value": null, "displayValue": "Price on Request", "unit": null, "deposit": null, "description": null}, "unitsAvailable": null, "areaConfig": [{"name": "Saleable Area", "areaInfo": {"value": 1530, "unit": "sq.ft", "displayArea": "1530.00"}}], "emi": null, "averagePrice": "Price on request", "floorPlan": null, "projectAttributes": null, "features": null, "additionalFields": [{"id": "bedroom", "value": "3", "label": "Bedroom"}]}]}], [{"key": "3", "label": "2 BHK", "propertyTypeName": "Apartment", "propertyTypeId": 1, "range": null, "data": [{"id": "911599", "price": {"value": null, "displayValue": "Price on Request", "unit": null, "deposit": null, "description": null}, "unitsAvailable": null, "areaConfig": [{"name": "Carpet Area", "areaInfo": {"value": 544, "unit": "sq.ft", "displayArea": "544.00"}}], "emi": null, "averagePrice": "Price on request", "floorPlan": null, "projectAttributes": null, "features": null, "additionalFields": [{"id": "bedroom", "value": "2", "label": "Bedroom"}]}, {"id": "911600", "price": {"value": null, "displayValue": "Price on Request", "unit": null, "deposit": null, "description": null}, "unitsAvailable": null, "areaConfig": [{"name": "Carpet Area", "areaInfo": {"value": 572, "unit": "sq.ft", "displayArea": "572.00"}}], "emi": null, "averagePrice": "Price on request", "floorPlan": null, "projectAttributes": null, "features": null, "additionalFields": [{"id": "bedroom", "value": "2", "label": "Bedroom"}]}]}], [{"key": "2", "label": "1 BHK", "propertyTypeName": "Apartment", "propertyTypeId": 1, "range": null, "data": [{"id": "956228", "price": {"value": null, "displayValue": "Price on Request", "unit": null, "deposit": null, "description": null}, "unitsAvailable": null, "areaConfig": [{"name": "Carpet Area", "areaInfo": {"value": 371, "unit": "sq.ft", "displayArea": "371.00"}}], "emi": null, "averagePrice": "Price on request", "floorPlan": null, "projectAttributes": null, "features": null, "additionalFields": [{"id": "bedroom", "value": "1", "label": "Bedroom"}]}]}, {"key": "3", "label": "2 BHK", "propertyTypeName": "Apartment", "propertyTypeId": 1, "range": null, "data": [{"id": "956229", "price": {"value": null, "displayValue": "Price on Request", "unit": null, "deposit": null, "description": null}, "unitsAvailable": null, "areaConfig": [{"name": "Carpet Area", "areaInfo": {"value": 521, "unit": "sq.ft", "displayArea": "521.00"}}], "emi": null, "averagePrice": "Price on request", "floorPlan": null, "projectAttributes": null, "features": null, "additionalFields": [{"id": "bedroom", "value": "2", "label": "Bedroom"}]}]}], [], [], [], [{"key": "54", "label": "Plots/Agriculture land", "propertyTypeName": "Plot", "propertyTypeId": 15, "range": null, "data": [{"id": "734983", "price": {"value": null, "displayValue": "Price on Request", "unit": null, "deposit": null, "description": null}, "unitsAvailable": null, "areaConfig": [{"name": "Plot Area", "areaInfo": {"value": 1076, "unit": "sq.ft", "displayArea": "1076.00"}}], "emi": null, "averagePrice": "Price on request", "floorPlan": null, "projectAttributes": null, "features": null, "additionalFields": []}, {"id": "734984", "price": {"value": null, "displayValue": "Price on Request", "unit": null, "deposit": null, "description": null}, "unitsAvailable": null, "areaConfig": [{"name": "Plot Area", "areaInfo": {"value": 1615, "unit": "sq.ft", "displayArea": "1615.00"}}], "emi": null, "averagePrice": "Price on request", "floorPlan": null, "projectAttributes": null, "features": null, "additionalFields": []}, {"id": "734985", "price": {"value": null, "displayValue": "Price on Request", "unit": null, "deposit": null, "description": null}, "unitsAvailable": null, "areaConfig": [{"name": "Plot Area", "areaInfo": {"value": 2153, "unit": "sq.ft", "displayArea": "2153.00"}}], "emi": null, "averagePrice": "Price on request", "floorPlan": null, "projectAttributes": null, "features": null, "additionalFields": []}, {"id": "734986", "price": {"value": null, "displayValue": "Price on Request", "unit": null, "deposit": null, "description": null}, "unitsAvailable": null, "areaConfig": [{"name": "Plot Area", "areaInfo": {"value": 2691, "unit": "sq.ft", "displayArea": "2691.00"}}], "emi": null, "averagePrice": "Price on request", "floorPlan": null, "projectAttributes": null, "features": null, "additionalFields": []}, {"id": "734987", "price": {"value": null, "displayValue": "Price on Request", "unit": null, "deposit": null, "description": null}, "unitsAvailable": null, "areaConfig": [{"name": "Plot Area", "areaInfo": {"value": 5382, "unit": "sq.ft", "displayArea": "5382.00"}}], "emi": null, "averagePrice": "Price on request", "floorPlan": null, "projectAttributes": null, "features": null, "additionalFields": []}]}], [], [{"key": "3", "label": "2 BHK", "propertyTypeName": "Apartment", "propertyTypeId": 1, "range": null, "data": [{"id": "476436", "price": {"value": 1799820, "displayValue": "\u20b9 18.0 L", "unit": null, "deposit": null, "description": null}, "unitsAvailable": null, "areaConfig": [{"name": "Carpet Area", "areaInfo": {"value": 660, "unit": "sq.ft", "displayArea": "660.00"}}], "emi": null, "averagePrice": "\u20b92.73K per sq.ft", "floorPlan": null, "projectAttributes": null, "features": null, "additionalFields": [{"id": "bedroom", "value": "2", "label": "Bedroom"}]}]}], [], [{"key": "2", "label": "1 BHK", "propertyTypeName": "Apartment", "propertyTypeId": 1, "range": null, "data": [{"id": "736958", "price": {"value": null, "displayValue": "Price on Request", "unit": null, "deposit": null, "description": null}, "unitsAvailable": null, "areaConfig": [{"name": "Carpet Area", "areaInfo": {"value": 354, "unit": "sq.ft", "displayArea": "354.00"}}], "emi": null, "averagePrice": "Price on request", "floorPlan": null, "projectAttributes": null, "features": null, "additionalFields": [{"id": "bedroom", "value": "1", "label": "Bedroom"}]}]}], [{"key": "2", "label": "1 BHK", "propertyTypeName": "Apartment", "propertyTypeId": 1, "range": null, "data": [{"id": "907742", "price": {"value": null, "displayValue": "Price on Request", "unit": null, "deposit": null, "description": null}, "unitsAvailable": null, "areaConfig": [{"name": "Carpet Area", "areaInfo": {"value": 404, "unit": "sq.ft", "displayArea": "404.00"}}], "emi": null, "averagePrice": "Price on request", "floorPlan": null, "projectAttributes": null, "features": null, "additionalFields": [{"id": "bedroom", "value": "1", "label": "Bedroom"}]}, {"id": "907743", "price": {"value": null, "displayValue": "Price on Request", "unit": null, "deposit": null, "description": null}, "unitsAvailable": null, "areaConfig": [{"name": "Carpet Area", "areaInfo": {"value": 448, "unit": "sq.ft", "displayArea": "448.00"}}], "emi": null, "averagePrice": "Price on request", "floorPlan": null, "projectAttributes": null, "features": null, "additionalFields": [{"id": "bedroom", "value": "1", "label": "Bedroom"}]}]}, {"key": "3", "label": "2 BHK", "propertyTypeName": "Apartment", "propertyTypeId": 1, "range": null, "data": [{"id": "907744", "price": {"value": null, "displayValue": "Price on Request", "unit": null, "deposit": null, "description": null}, "unitsAvailable": null, "areaConfig": [{"name": "Carpet Area", "areaInfo": {"value": 498, "unit": "sq.ft", "displayArea": "498.00"}}], "emi": null, "averagePrice": "Price on request", "floorPlan": null, "projectAttributes": null, "features": null, "additionalFields": [{"id": "bedroom", "value": "2", "label": "Bedroom"}]}, {"id": "907745", "price": {"value": null, "displayValue": "Price on Request", "unit": null, "deposit": null, "description": null}, "unitsAvailable": null, "areaConfig": [{"name": "Carpet Area", "areaInfo": {"value": 609, "unit": "sq.ft", "displayArea": "609.00"}}], "emi": null, "averagePrice": "Price on request", "floorPlan": null, "projectAttributes": null, "features": null, "additionalFields": [{"id": "bedroom", "value": "2", "label": "Bedroom"}]}]}, {"key": "4", "label": "3 BHK", "propertyTypeName": "Apartment", "propertyTypeId": 1, "range": null, "data": [{"id": "907746", "price": {"value": null, "displayValue": "Price on Request", "unit": null, "deposit": null, "description": null}, "unitsAvailable": null, "areaConfig": [{"name": "Carpet Area", "areaInfo": {"value": 758, "unit": "sq.ft", "displayArea": "758.00"}}], "emi": null, "averagePrice": "Price on request", "floorPlan": null, "projectAttributes": null, "features": null, "additionalFields": [{"id": "bedroom", "value": "3", "label": "Bedroom"}]}, {"id": "907747", "price": {"value": null, "displayValue": "Price on Request", "unit": null, "deposit": null, "description": null}, "unitsAvailable": null, "areaConfig": [{"name": "Carpet Area", "areaInfo": {"value": 765, "unit": "sq.ft", "displayArea": "765.00"}}], "emi": null, "averagePrice": "Price on request", "floorPlan": null, "projectAttributes": null, "features": null, "additionalFields": [{"id": "bedroom", "value": "3", "label": "Bedroom"}]}]}], [], [], [{"key": "3", "label": "2 BHK", "propertyTypeName": "Apartment", "propertyTypeId": 1, "range": null, "data": [{"id": "70915", "price": {"value": 4199850, "displayValue": "\u20b9 42.0 L", "unit": null, "deposit": null, "description": null}, "unitsAvailable": null, "areaConfig": [{"name": "Saleable Area", "areaInfo": {"value": 1350, "unit": "sq.ft", "displayArea": "1350.00"}}], "emi": "\u20b922.24 K", "averagePrice": "\u20b93.11K per sq.ft", "floorPlan": [{"src": "https://is1-2.housingcdn.com/91aba65c/1029797ce57e005220424f48449dacb6/v8/version.jpg", "alt": null, "tag": "2D", "floor": null, "caption": "2 BHK, undefined sq.ft", "type": null}], "projectAttributes": null, "features": null, "additionalFields": [{"id": "bedroom", "value": "2", "label": "Bedroom"}, {"id": "balcony", "value": "2", "label": "Balcony"}, {"id": "bathroom", "value": "1", "label": "Bathroom"}]}]}], [], [{"key": "4", "label": "3 BHK", "propertyTypeName": "Builder Floor", "propertyTypeId": 14, "range": null, "data": [{"id": "629429", "price": {"value": 23100000, "displayValue": "\u20b9 2.31 Cr", "unit": null, "deposit": null, "description": null}, "unitsAvailable": null, "areaConfig": [{"name": "Builtup Area", "areaInfo": {"value": 1250, "unit": "sq.ft", "displayArea": "1250.00"}}], "emi": null, "averagePrice": "\u20b915.71K per sq.ft", "floorPlan": null, "projectAttributes": null, "features": null, "additionalFields": [{"id": "bedroom", "value": "3", "label": "Bedroom"}]}, {"id": "629430", "price": {"value": 30000000, "displayValue": "\u20b9 3 Cr", "unit": null, "deposit": null, "description": null}, "unitsAvailable": null, "areaConfig": [{"name": "Builtup Area", "areaInfo": {"value": 1500, "unit": "sq.ft", "displayArea": "1500.00"}}], "emi": null, "averagePrice": "\u20b917K per sq.ft", "floorPlan": null, "projectAttributes": null, "features": null, "additionalFields": [{"id": "bedroom", "value": "3", "label": "Bedroom"}]}]}], [], [{"key": "2", "label": "1 BHK", "propertyTypeName": "Apartment", "propertyTypeId": 1, "range": null, "data": [{"id": "664822", "price": {"value": null, "displayValue": "Price on Request", "unit": null, "deposit": null, "description": null}, "unitsAvailable": null, "areaConfig": [{"name": "Carpet Area", "areaInfo": {"value": 265, "unit": "sq.ft", "displayArea": "265.00"}}], "emi": null, "averagePrice": "\u20b925K per sq.ft", "floorPlan": null, "projectAttributes": null, "features": null, "additionalFields": [{"id": "bedroom", "value": "1", "label": "Bedroom"}]}, {"id": "664823", "price": {"value": null, "displayValue": "Price on Request", "unit": null, "deposit": null, "description": null}, "unitsAvailable": null, "areaConfig": [{"name": "Carpet Area", "areaInfo": {"value": 351, "unit": "sq.ft", "displayArea": "351.00"}}], "emi": null, "averagePrice": "\u20b925K per sq.ft", "floorPlan": null, "projectAttributes": null, "features": null, "additionalFields": [{"id": "bedroom", "value": "1", "label": "Bedroom"}]}, {"id": "664824", "price": {"value": null, "displayValue": "Price on Request", "unit": null, "deposit": null, "description": null}, "unitsAvailable": null, "areaConfig": [{"name": "Carpet Area", "areaInfo": {"value": 420, "unit": "sq.ft", "displayArea": "420.00"}}], "emi": null, "averagePrice": "\u20b925K per sq.ft", "floorPlan": null, "projectAttributes": null, "features": null, "additionalFields": [{"id": "bedroom", "value": "1", "label": "Bedroom"}]}, {"id": "664821", "price": {"value": null, "displayValue": "Price on Request", "unit": null, "deposit": null, "description": null}, "unitsAvailable": null, "areaConfig": [{"name": "Carpet Area", "areaInfo": {"value": 460, "unit": "sq.ft", "displayArea": "460.00"}}], "emi": null, "averagePrice": "\u20b925K per sq.ft", "floorPlan": null, "projectAttributes": null, "features": null, "additionalFields": [{"id": "bedroom", "value": "1", "label": "Bedroom"}]}, {"id": "664820", "price": {"value": null, "displayValue": "Price on Request", "unit": null, "deposit": null, "description": null}, "unitsAvailable": null, "areaConfig": [{"name": "Carpet Area", "areaInfo": {"value": 470, "unit": "sq.ft", "displayArea": "470.00"}}], "emi": null, "averagePrice": "\u20b925K per sq.ft", "floorPlan": null, "projectAttributes": null, "features": null, "additionalFields": [{"id": "bedroom", "value": "1", "label": "Bedroom"}]}]}, {"key": "3", "label": "2 BHK", "propertyTypeName": "Apartment", "propertyTypeId": 1, "range": null, "data": [{"id": "664825", "price": {"value": null, "displayValue": "Price on Request", "unit": null, "deposit": null, "description": null}, "unitsAvailable": null, "areaConfig": [{"name": "Carpet Area", "areaInfo": {"value": 660, "unit": "sq.ft", "displayArea": "660.00"}}], "emi": null, "averagePrice": "\u20b925K per sq.ft", "floorPlan": null, "projectAttributes": null, "features": null, "additionalFields": [{"id": "bedroom", "value": "2", "label": "Bedroom"}]}]}], [], [], [], [], [], [], [{"key": "5", "label": "4 BHK", "propertyTypeName": "Villa", "propertyTypeId": 108, "range": null, "data": [{"id": "888819", "price": {"value": 19101000, "displayValue": "\u20b9 1.91 Cr", "unit": null, "deposit": null, "description": null}, "unitsAvailable": null, "areaConfig": [{"name": "Carpet Area", "areaInfo": {"value": 3000, "unit": "sq.ft", "displayArea": "3000.00"}}, {"name": "Super Builtup Area", "areaInfo": {"value": 4000, "unit": "sq.ft", "displayArea": "4000.00"}}], "emi": null, "averagePrice": "\u20b96.37K per sq.ft", "floorPlan": [{"src": "https://is1-3.housingcdn.com/91aba65c/479ee55fde05564717d5762c73d52d29/v0/version.jpeg", "alt": null, "tag": "2D", "floor": null, "caption": "4 BHK, undefined sq.ft", "type": null}], "projectAttributes": null, "features": null, "additionalFields": [{"id": "bedroom", "value": "4", "label": "Bedroom"}]}]}], [], [{"key": "3", "label": "2 BHK", "propertyTypeName": "Apartment", "propertyTypeId": 1, "range": null, "data": [{"id": "627115", "price": {"value": null, "displayValue": "Price on Request", "unit": null, "deposit": null, "description": null}, "unitsAvailable": null, "areaConfig": [{"name": "Carpet Area", "areaInfo": {"value": 506, "unit": "sq.ft", "displayArea": "506.00"}}], "emi": null, "averagePrice": "Price on request", "floorPlan": null, "projectAttributes": null, "features": null, "additionalFields": [{"id": "bedroom", "value": "2", "label": "Bedroom"}]}]}], [], [], [{"key": "3", "label": "2 BHK", "propertyTypeName": "Apartment", "propertyTypeId": 1, "range": null, "data": [{"id": "74062", "price": {"value": 4611600, "displayValue": "\u20b9 46.12 L", "unit": null, "deposit": null, "description": null}, "unitsAvailable": null, "areaConfig": [{"name": "Saleable Area", "areaInfo": {"value": 1098, "unit": "sq.ft", "displayArea": "1098.00"}}], "emi": "\u20b924.42 K", "averagePrice": "\u20b94.2K per sq.ft", "floorPlan": [{"src": "https://is1-3.housingcdn.com/91aba65c/cc2e0dd57d8a25fe0bebc80d6c404657/v8/version.jpg", "alt": null, "tag": "2D", "floor": null, "caption": "2 BHK, undefined sq.ft", "type": null}, {"src": "https://is1-3.housingcdn.com/91aba65c/adcd6f946d1720d8c768dfdf3d166d60/v8/version.jpg", "alt": null, "tag": "3D", "floor": null, "caption": "2 BHK, undefined sq.ft", "type": null}], "projectAttributes": null, "features": null, "additionalFields": [{"id": "bedroom", "value": "2", "label": "Bedroom"}, {"id": "balcony", "value": "2", "label": "Balcony"}, {"id": "bathroom", "value": "3", "label": "Bathroom"}]}]}, {"key": "4", "label": "3 BHK", "propertyTypeName": "Apartment", "propertyTypeId": 1, "range": null, "data": [{"id": "74063", "price": {"value": 5371800, "displayValue": "\u20b9 53.72 L", "unit": null, "deposit": null, "description": null}, "unitsAvailable": null, "areaConfig": [{"name": "Saleable Area", "areaInfo": {"value": 1279, "unit": "sq.ft", "displayArea": "1279.00"}}], "emi": "\u20b928.45 K", "averagePrice": "\u20b94.2K per sq.ft", "floorPlan": [{"src": "https://is1-3.housingcdn.com/91aba65c/a94415e6ca6428f6f049208a3542961b/v8/version.jpg", "alt": null, "tag": "2D", "floor": null, "caption": "3 BHK, undefined sq.ft", "type": null}, {"src": "https://is1-3.housingcdn.com/91aba65c/4344fedc3f754427df7844078075f3b7/v8/version.jpg", "alt": null, "tag": "3D", "floor": null, "caption": "3 BHK, undefined sq.ft", "type": null}], "projectAttributes": null, "features": null, "additionalFields": [{"id": "bedroom", "value": "3", "label": "Bedroom"}, {"id": "balcony", "value": "2", "label": "Balcony"}, {"id": "bathroom", "value": "3", "label": "Bathroom"}]}, {"id": "74064", "price": {"value": 6934200, "displayValue": "\u20b9 69.34 L", "unit": null, "deposit": null, "description": null}, "unitsAvailable": null, "areaConfig": [{"name": "Saleable Area", "areaInfo": {"value": 1651, "unit": "sq.ft", "displayArea": "1651.00"}}], "emi": "\u20b936.72 K", "averagePrice": "\u20b94.2K per sq.ft", "floorPlan": [{"src": "https://is1-3.housingcdn.com/91aba65c/bba0f87c453fe51e789839aa77e248a2/v8/version.jpg", "alt": null, "tag": "2D", "floor": null, "caption": "3 BHK, undefined sq.ft", "type": null}, {"src": "https://is1-3.housingcdn.com/91aba65c/c7afe0708294145705aef561e26a66c2/v8/version.jpg", "alt": null, "tag": "3D", "floor": null, "caption": "3 BHK, undefined sq.ft", "type": null}], "projectAttributes": null, "features": null, "additionalFields": [{"id": "bedroom", "value": "3", "label": "Bedroom"}, {"id": "balcony", "value": "1", "label": "Balcony"}, {"id": "bathroom", "value": "3", "label": "Bathroom"}]}]}], [], [], [], [], [{"key": "3", "label": "2 BHK", "propertyTypeName": "Apartment", "propertyTypeId": 1, "range": null, "data": [{"id": "671451", "price": {"value": 4095000, "displayValue": "\u20b9 40.95 L", "unit": null, "deposit": null, "description": null}, "unitsAvailable": null, "areaConfig": [{"name": "Builtup Area", "areaInfo": {"value": 975, "unit": "sq.ft", "displayArea": "975.00"}}], "emi": null, "averagePrice": "\u20b94.2K per sq.ft", "floorPlan": null, "projectAttributes": null, "features": null, "additionalFields": [{"id": "bedroom", "value": "2", "label": "Bedroom"}]}, {"id": "671454", "price": {"value": 5040000, "displayValue": "\u20b9 50.4 L", "unit": null, "deposit": null, "description": null}, "unitsAvailable": null, "areaConfig": [{"name": "Builtup Area", "areaInfo": {"value": 1200, "unit": "sq.ft", "displayArea": "1200.00"}}], "emi": null, "averagePrice": "\u20b94.2K per sq.ft", "floorPlan": null, "projectAttributes": null, "features": null, "additionalFields": [{"id": "bedroom", "value": "2", "label": "Bedroom"}]}]}, {"key": "4", "label": "3 BHK", "propertyTypeName": "Apartment", "propertyTypeId": 1, "range": null, "data": [{"id": "671452", "price": {"value": 5166000, "displayValue": "\u20b9 51.66 L", "unit": null, "deposit": null, "description": null}, "unitsAvailable": null, "areaConfig": [{"name": "Builtup Area", "areaInfo": {"value": 1230, "unit": "sq.ft", "displayArea": "1230.00"}}], "emi": null, "averagePrice": "\u20b94.2K per sq.ft", "floorPlan": null, "projectAttributes": null, "features": null, "additionalFields": [{"id": "bedroom", "value": "3", "label": "Bedroom"}]}, {"id": "671453", "price": {"value": 5691000, "displayValue": "\u20b9 56.91 L", "unit": null, "deposit": null, "description": null}, "unitsAvailable": null, "areaConfig": [{"name": "Builtup Area", "areaInfo": {"value": 1355, "unit": "sq.ft", "displayArea": "1355.00"}}], "emi": null, "averagePrice": "\u20b94.2K per sq.ft", "floorPlan": null, "projectAttributes": null, "features": null, "additionalFields": [{"id": "bedroom", "value": "3", "label": "Bedroom"}]}]}], [{"key": "45", "label": "4.5 BHK", "propertyTypeName": "Villa", "propertyTypeId": 108, "range": null, "data": [{"id": "682731", "price": {"value": 23999424, "displayValue": "\u20b9 2.4 Cr", "unit": null, "deposit": null, "description": null}, "unitsAvailable": null, "areaConfig": [{"name": "Super Builtup Area", "areaInfo": {"value": 3824, "unit": "sq.ft", "displayArea": "3824.00"}}], "emi": null, "averagePrice": "\u20b96.28K per sq.ft", "floorPlan": null, "projectAttributes": null, "features": null, "additionalFields": [{"id": "bedroom", "value": "4", "label": "Bedroom"}, {"id": "study", "value": "1", "label": "Study Room"}]}, {"id": "682732", "price": {"value": 23999976, "displayValue": "\u20b9 2.4 Cr", "unit": null, "deposit": null, "description": null}, "unitsAvailable": null, "areaConfig": [{"name": "Super Builtup Area", "areaInfo": {"value": 4212, "unit": "sq.ft", "displayArea": "4212.00"}}], "emi": null, "averagePrice": "\u20b95.7K per sq.ft", "floorPlan": null, "projectAttributes": null, "features": null, "additionalFields": [{"id": "bedroom", "value": "4", "label": "Bedroom"}, {"id": "study", "value": "1", "label": "Study Room"}]}]}], [], [{"key": "3", "label": "2 BHK", "propertyTypeName": "Apartment", "propertyTypeId": 1, "range": null, "data": [{"id": "931271", "price": {"value": 4700080, "displayValue": "\u20b9 47.0 L", "unit": null, "deposit": null, "description": null}, "unitsAvailable": null, "areaConfig": [{"name": "Saleable Area", "areaInfo": {"value": 1090, "unit": "sq.ft", "displayArea": "1090.00"}}], "emi": "\u20b924.89 K", "averagePrice": "\u20b94.31K per sq.ft", "floorPlan": [{"src": "https://is1-3.housingcdn.com/91aba65c/1ee47d683ed4309c4b1a551d96964807/v0/version.jpeg", "alt": null, "tag": "2D", "floor": null, "caption": "2 BHK, undefined sq.ft", "type": null}, {"src": "https://is1-2.housingcdn.com/91aba65c/c8c48ba9e2fb5ca95172eb4aa39442ef/v0/version.jpg", "alt": null, "tag": "3D", "floor": null, "caption": "2 BHK, undefined sq.ft", "type": null}], "projectAttributes": null, "features": null, "additionalFields": [{"id": "bedroom", "value": "2", "label": "Bedroom"}]}]}], [{"key": "2", "label": "1 BHK", "propertyTypeName": "Apartment", "propertyTypeId": 1, "range": null, "data": [{"id": "810091", "price": {"value": 2558130.24, "displayValue": "\u20b9 25.58 L", "unit": null, "deposit": null, "description": null}, "unitsAvailable": null, "areaConfig": [{"name": "Carpet Area", "areaInfo": {"value": 462, "unit": "sq.ft", "displayArea": "462.00"}}], "emi": null, "averagePrice": "\u20b95.54K per sq.ft", "floorPlan": null, "projectAttributes": null, "features": null, "additionalFields": [{"id": "bedroom", "value": "1", "label": "Bedroom"}]}, {"id": "810090", "price": {"value": 2640395.2, "displayValue": "\u20b9 26.4 L", "unit": null, "deposit": null, "description": null}, "unitsAvailable": null, "areaConfig": [{"name": "Carpet Area", "areaInfo": {"value": 477, "unit": "sq.ft", "displayArea": "477.00"}}], "emi": null, "averagePrice": "\u20b95.54K per sq.ft", "floorPlan": null, "projectAttributes": null, "features": null, "additionalFields": [{"id": "bedroom", "value": "1", "label": "Bedroom"}]}]}, {"key": "3", "label": "2 BHK", "propertyTypeName": "Apartment", "propertyTypeId": 1, "range": null, "data": [{"id": "810092", "price": {"value": 3742169.92, "displayValue": "\u20b9 37.42 L", "unit": null, "deposit": null, "description": null}, "unitsAvailable": null, "areaConfig": [{"name": "Carpet Area", "areaInfo": {"value": 676, "unit": "sq.ft", "displayArea": "676.00"}}], "emi": null, "averagePrice": "\u20b95.54K per sq.ft", "floorPlan": null, "projectAttributes": null, "features": null, "additionalFields": [{"id": "bedroom", "value": "2", "label": "Bedroom"}]}]}], [], [{"key": "4", "label": "3 BHK", "propertyTypeName": "Apartment", "propertyTypeId": 1, "range": null, "data": [{"id": "309355", "price": {"value": 33580000, "displayValue": "\u20b9 3.36 Cr", "unit": null, "deposit": null, "description": null}, "unitsAvailable": null, "areaConfig": [{"name": "Builtup Area", "areaInfo": {"value": 4600, "unit": "sq.ft", "displayArea": "4600.00"}}], "emi": null, "averagePrice": "\u20b97.3K per sq.ft", "floorPlan": [{"src": "https://is1-2.housingcdn.com/91aba65c/654f8cdbbc517294123112f76c5ae110/v0/version.jpeg", "alt": null, "tag": "2D", "floor": null, "caption": "3 BHK, undefined sq.ft", "type": null}], "projectAttributes": null, "features": null, "additionalFields": [{"id": "bedroom", "value": "3", "label": "Bedroom"}]}]}, {"key": "45", "label": "4.5 BHK", "propertyTypeName": "Apartment", "propertyTypeId": 1, "range": null, "data": [{"id": "309356", "price": {"value": 40150000, "displayValue": "\u20b9 4.02 Cr", "unit": null, "deposit": null, "description": null}, "unitsAvailable": null, "areaConfig": [{"name": "Builtup Area", "areaInfo": {"value": 5500, "unit": "sq.ft", "displayArea": "5500.00"}}], "emi": null, "averagePrice": "\u20b97.3K per sq.ft", "floorPlan": [{"src": "https://is1-3.housingcdn.com/91aba65c/afc789ff913038e2fe87707ff7fccc3c/v2/version.jpeg", "alt": null, "tag": "2D", "floor": null, "caption": "4.5 BHK, undefined sq.ft", "type": null}, {"src": "https://is1-3.housingcdn.com/91aba65c/e39267d78dbd448a3f499bfa20991a56/v2/version.jpg", "alt": null, "tag": "3D", "floor": null, "caption": "4.5 BHK, undefined sq.ft", "type": null}], "projectAttributes": null, "features": null, "additionalFields": [{"id": "bedroom", "value": "4", "label": "Bedroom"}, {"id": "study", "value": "1", "label": "Study Room"}]}]}], [], [{"key": "3", "label": "2 BHK", "propertyTypeName": "Apartment", "propertyTypeId": 1, "range": null, "data": [{"id": "766541", "price": {"value": null, "displayValue": "Price on Request", "unit": null, "deposit": null, "description": null}, "unitsAvailable": null, "areaConfig": [{"name": "Builtup Area", "areaInfo": {"value": 830, "unit": "sq.ft", "displayArea": "830.00"}}], "emi": null, "averagePrice": "Price on request", "floorPlan": null, "projectAttributes": null, "features": null, "additionalFields": [{"id": "bedroom", "value": "2", "label": "Bedroom"}]}]}], [], [{"key": "2", "label": "1 BHK", "propertyTypeName": "Apartment", "propertyTypeId": 1, "range": null, "data": [{"id": "898993", "price": {"value": 3500359.9, "displayValue": "\u20b9 35.0 L", "unit": null, "deposit": null, "description": null}, "unitsAvailable": null, "areaConfig": [{"name": "Carpet Area", "areaInfo": {"value": 374, "unit": "sq.ft", "displayArea": "374.00"}}], "emi": null, "averagePrice": "\u20b99.36K per sq.ft", "floorPlan": [{"src": "https://is1-2.housingcdn.com/91aba65c/50a009e2d4fa71e8057e5d48ee04aaf2/v0/version.jpeg", "alt": null, "tag": "2D", "floor": null, "caption": "1 BHK, undefined sq.ft", "type": null}], "projectAttributes": null, "features": null, "additionalFields": [{"id": "bedroom", "value": "1", "label": "Bedroom"}]}]}, {"key": "3", "label": "2 BHK", "propertyTypeName": "Apartment", "propertyTypeId": 1, "range": null, "data": [{"id": "898994", "price": {"value": 4500069.52, "displayValue": "\u20b9 45.0 L", "unit": null, "deposit": null, "description": null}, "unitsAvailable": null, "areaConfig": [{"name": "Carpet Area", "areaInfo": {"value": 516, "unit": "sq.ft", "displayArea": "516.00"}}], "emi": null, "averagePrice": "\u20b98.73K per sq.ft", "floorPlan": [{"src": "https://is1-3.housingcdn.com/91aba65c/4e43aca80ffb4da5f8e97b934a5dbb8c/v0/version.jpeg", "alt": null, "tag": "2D", "floor": null, "caption": "2 BHK, undefined sq.ft", "type": null}], "projectAttributes": null, "features": null, "additionalFields": [{"id": "bedroom", "value": "2", "label": "Bedroom"}]}]}], [], [], [{"key": "3", "label": "2 BHK", "propertyTypeName": "Apartment", "propertyTypeId": 1, "range": null, "data": [{"id": "667000", "price": {"value": 3021200, "displayValue": "\u20b9 30.21 L", "unit": null, "deposit": null, "description": null}, "unitsAvailable": null, "areaConfig": [{"name": "Builtup Area", "areaInfo": {"value": 1079, "unit": "sq.ft", "displayArea": "1079.00"}}], "emi": null, "averagePrice": "\u20b92.8K per sq.ft", "floorPlan": null, "projectAttributes": null, "features": null, "additionalFields": [{"id": "bedroom", "value": "2", "label": "Bedroom"}]}]}, {"key": "4", "label": "3 BHK", "propertyTypeName": "Apartment", "propertyTypeId": 1, "range": null, "data": [{"id": "667001", "price": {"value": 3894000, "displayValue": "\u20b9 38.94 L", "unit": null, "deposit": null, "description": null}, "unitsAvailable": null, "areaConfig": [{"name": "Builtup Area", "areaInfo": {"value": 1298, "unit": "sq.ft", "displayArea": "1298.00"}}], "emi": null, "averagePrice": "\u20b93K per sq.ft", "floorPlan": null, "projectAttributes": null, "features": null, "additionalFields": [{"id": "bedroom", "value": "3", "label": "Bedroom"}]}]}], [], [{"key": "2", "label": "1 BHK", "propertyTypeName": "Apartment", "propertyTypeId": 1, "range": null, "data": [{"id": "757219", "price": {"value": null, "displayValue": "Price on Request", "unit": null, "deposit": null, "description": null}, "unitsAvailable": null, "areaConfig": [{"name": "Super Builtup Area", "areaInfo": {"value": 450, "unit": "sq.ft", "displayArea": "450.00"}}], "emi": null, "averagePrice": "Price on request", "floorPlan": null, "projectAttributes": null, "features": null, "additionalFields": [{"id": "bedroom", "value": "1", "label": "Bedroom"}]}]}, {"key": "3", "label": "2 BHK", "propertyTypeName": "Apartment", "propertyTypeId": 1, "range": null, "data": [{"id": "757220", "price": {"value": null, "displayValue": "Price on Request", "unit": null, "deposit": null, "description": null}, "unitsAvailable": null, "areaConfig": [{"name": "Super Builtup Area", "areaInfo": {"value": 900, "unit": "sq.ft", "displayArea": "900.00"}}], "emi": null, "averagePrice": "Price on request", "floorPlan": null, "projectAttributes": null, "features": null, "additionalFields": [{"id": "bedroom", "value": "2", "label": "Bedroom"}]}, {"id": "757221", "price": {"value": null, "displayValue": "Price on Request", "unit": null, "deposit": null, "description": null}, "unitsAvailable": null, "areaConfig": [{"name": "Super Builtup Area", "areaInfo": {"value": 1200, "unit": "sq.ft", "displayArea": "1200.00"}}], "emi": null, "averagePrice": "Price on request", "floorPlan": null, "projectAttributes": null, "features": null, "additionalFields": [{"id": "bedroom", "value": "2", "label": "Bedroom"}]}]}, {"key": "4", "label": "3 BHK", "propertyTypeName": "Apartment", "propertyTypeId": 1, "range": null, "data": [{"id": "757222", "price": {"value": null, "displayValue": "Price on Request", "unit": null, "deposit": null, "description": null}, "unitsAvailable": null, "areaConfig": [{"name": "Super Builtup Area", "areaInfo": {"value": 1300, "unit": "sq.ft", "displayArea": "1300.00"}}], "emi": null, "averagePrice": "Price on request", "floorPlan": null, "projectAttributes": null, "features": null, "additionalFields": [{"id": "bedroom", "value": "3", "label": "Bedroom"}]}, {"id": "757223", "price": {"value": null, "displayValue": "Price on Request", "unit": null, "deposit": null, "description": null}, "unitsAvailable": null, "areaConfig": [{"name": "Super Builtup Area", "areaInfo": {"value": 1500, "unit": "sq.ft", "displayArea": "1500.00"}}], "emi": null, "averagePrice": "Price on request", "floorPlan": null, "projectAttributes": null, "features": null, "additionalFields": [{"id": "bedroom", "value": "3", "label": "Bedroom"}]}]}], [{"key": "3", "label": "2 BHK", "propertyTypeName": "Apartment", "propertyTypeId": 1, "range": null, "data": [{"id": "809730", "price": {"value": 4400000, "displayValue": "\u20b9 44 L", "unit": null, "deposit": null, "description": null}, "unitsAvailable": null, "areaConfig": [{"name": "Builtup Area", "areaInfo": {"value": 1073, "unit": "sq.ft", "displayArea": "1073.00"}}], "emi": null, "averagePrice": "\u20b93.49K per sq.ft", "floorPlan": null, "projectAttributes": null, "features": null, "additionalFields": [{"id": "bedroom", "value": "2", "label": "Bedroom"}]}, {"id": "809729", "price": {"value": 4600000, "displayValue": "\u20b9 46 L", "unit": null, "deposit": null, "description": null}, "unitsAvailable": null, "areaConfig": [{"name": "Builtup Area", "areaInfo": {"value": 1134, "unit": "sq.ft", "displayArea": "1134.00"}}], "emi": null, "averagePrice": "\u20b93.45K per sq.ft", "floorPlan": null, "projectAttributes": null, "features": null, "additionalFields": [{"id": "bedroom", "value": "2", "label": "Bedroom"}]}]}, {"key": "4", "label": "3 BHK", "propertyTypeName": "Apartment", "propertyTypeId": 1, "range": null, "data": [{"id": "809726", "price": {"value": 5500000, "displayValue": "\u20b9 55 L", "unit": null, "deposit": null, "description": null}, "unitsAvailable": null, "areaConfig": [{"name": "Builtup Area", "areaInfo": {"value": 1392, "unit": "sq.ft", "displayArea": "1392.00"}}], "emi": null, "averagePrice": "\u20b93.36K per sq.ft", "floorPlan": [{"src": "https://is1-3.housingcdn.com/91aba65c/3e196f6b04f66bd82fffdf1fe8f8e67a/v0/version.jpeg", "alt": null, "tag": "2D", "floor": null, "caption": "3 BHK, undefined sq.ft", "type": null}, {"src": "https://is1-3.housingcdn.com/91aba65c/39df1da3f6ce2e877839d5442d7e38ef/v0/version.jpg", "alt": null, "tag": "3D", "floor": null, "caption": "3 BHK, undefined sq.ft", "type": null}], "projectAttributes": null, "features": null, "additionalFields": [{"id": "bedroom", "value": "3", "label": "Bedroom"}]}, {"id": "809727", "price": {"value": 5700000, "displayValue": "\u20b9 57 L", "unit": null, "deposit": null, "description": null}, "unitsAvailable": null, "areaConfig": [{"name": "Builtup Area", "areaInfo": {"value": 1408, "unit": "sq.ft", "displayArea": "1408.00"}}], "emi": null, "averagePrice": "\u20b93.44K per sq.ft", "floorPlan": [{"src": "https://is1-3.housingcdn.com/91aba65c/201944f645c91ea4f01aede6d76330b8/v0/version.jpeg", "alt": null, "tag": "2D", "floor": null, "caption": "3 BHK, undefined sq.ft", "type": null}, {"src": "https://is1-3.housingcdn.com/91aba65c/bb2528feaa4caa610f3c9c162742078f/v0/version.jpg", "alt": null, "tag": "3D", "floor": null, "caption": "3 BHK, undefined sq.ft", "type": null}], "projectAttributes": null, "features": null, "additionalFields": [{"id": "bedroom", "value": "3", "label": "Bedroom"}]}, {"id": "809728", "price": {"value": 5800000, "displayValue": "\u20b9 58 L", "unit": null, "deposit": null, "description": null}, "unitsAvailable": null, "areaConfig": [{"name": "Builtup Area", "areaInfo": {"value": 1500, "unit": "sq.ft", "displayArea": "1500.00"}}], "emi": null, "averagePrice": "\u20b93.29K per sq.ft", "floorPlan": [{"src": "https://is1-2.housingcdn.com/91aba65c/eab679fea32a9ebebe43e6f12e289573/v0/version.jpeg", "alt": null, "tag": "2D", "floor": null, "caption": "3 BHK, undefined sq.ft", "type": null}, {"src": "https://is1-3.housingcdn.com/91aba65c/c05e9cebe5c4b03e4ed9ee9163440410/v0/version.jpg", "alt": null, "tag": "3D", "floor": null, "caption": "3 BHK, undefined sq.ft", "type": null}], "projectAttributes": null, "features": null, "additionalFields": [{"id": "bedroom", "value": "3", "label": "Bedroom"}]}]}], [{"key": "54", "label": "Plots/Agriculture land", "propertyTypeName": "Plot", "propertyTypeId": 15, "range": null, "data": [{"id": "947083", "price": {"value": 19800000, "displayValue": "\u20b9 1.98 Cr", "unit": null, "deposit": null, "description": null}, "unitsAvailable": null, "areaConfig": [{"name": "Plot Area", "areaInfo": {"value": 177, "unit": "sq.yd", "displayArea": "177.00"}}], "emi": null, "averagePrice": "\u20b999K per sq.yd", "floorPlan": null, "projectAttributes": null, "features": null, "additionalFields": []}]}], [], [{"key": "3", "label": "2 BHK", "propertyTypeName": "Apartment", "propertyTypeId": 1, "range": null, "data": [{"id": "768696", "price": {"value": null, "displayValue": "Price on Request", "unit": null, "deposit": null, "description": null}, "unitsAvailable": null, "areaConfig": [{"name": "Super Builtup Area", "areaInfo": {"value": 1200, "unit": "sq.ft", "displayArea": "1200.00"}}], "emi": null, "averagePrice": "Price on request", "floorPlan": [{"src": "https://is1-2.housingcdn.com/91aba65c/599caa517560d7434354add1cfdccb30/v0/version.png", "alt": null, "tag": "2D", "floor": null, "caption": "2 BHK, undefined sq.ft", "type": null}], "projectAttributes": null, "features": null, "additionalFields": [{"id": "bedroom", "value": "2", "label": "Bedroom"}]}, {"id": "768697", "price": {"value": null, "displayValue": "Price on Request", "unit": null, "deposit": null, "description": null}, "unitsAvailable": null, "areaConfig": [{"name": "Super Builtup Area", "areaInfo": {"value": 1210, "unit": "sq.ft", "displayArea": "1210.00"}}], "emi": null, "averagePrice": "Price on request", "floorPlan": [{"src": "https://is1-2.housingcdn.com/91aba65c/b1045c4bffa693994b05d829f4959294/v0/version.png", "alt": null, "tag": "2D", "floor": null, "caption": "2 BHK, undefined sq.ft", "type": null}], "projectAttributes": null, "features": null, "additionalFields": [{"id": "bedroom", "value": "2", "label": "Bedroom"}]}]}, {"key": "4", "label": "3 BHK", "propertyTypeName": "Apartment", "propertyTypeId": 1, "range": null, "data": [{"id": "768698", "price": {"value": null, "displayValue": "Price on Request", "unit": null, "deposit": null, "description": null}, "unitsAvailable": null, "areaConfig": [{"name": "Super Builtup Area", "areaInfo": {"value": 1550, "unit": "sq.ft", "displayArea": "1550.00"}}], "emi": null, "averagePrice": "Price on request", "floorPlan": [{"src": "https://is1-3.housingcdn.com/91aba65c/761a21042126f71f89bb45a00d09b837/v0/version.png", "alt": null, "tag": "2D", "floor": null, "caption": "3 BHK, undefined sq.ft", "type": null}], "projectAttributes": null, "features": null, "additionalFields": [{"id": "bedroom", "value": "3", "label": "Bedroom"}]}, {"id": "768699", "price": {"value": null, "displayValue": "Price on Request", "unit": null, "deposit": null, "description": null}, "unitsAvailable": null, "areaConfig": [{"name": "Super Builtup Area", "areaInfo": {"value": 1712, "unit": "sq.ft", "displayArea": "1712.00"}}], "emi": null, "averagePrice": "Price on request", "floorPlan": [{"src": "https://is1-3.housingcdn.com/91aba65c/ea8616f289c35c54e51b54bea2c41703/v0/version.png", "alt": null, "tag": "2D", "floor": null, "caption": "3 BHK, undefined sq.ft", "type": null}], "projectAttributes": null, "features": null, "additionalFields": [{"id": "bedroom", "value": "3", "label": "Bedroom"}]}]}], [], [], [], [{"key": "3", "label": "2 BHK", "propertyTypeName": "Apartment", "propertyTypeId": 1, "range": null, "data": [{"id": "885566", "price": {"value": 3600000, "displayValue": "\u20b9 36 L", "unit": null, "deposit": null, "description": null}, "unitsAvailable": null, "areaConfig": [{"name": "Builtup Area", "areaInfo": {"value": 800, "unit": "sq.ft", "displayArea": "800.00"}}], "emi": null, "averagePrice": "\u20b94.5K per sq.ft", "floorPlan": null, "projectAttributes": null, "features": null, "additionalFields": [{"id": "bedroom", "value": "2", "label": "Bedroom"}]}]}], [], [], [{"key": "53", "label": "Studio", "propertyTypeName": "Studio Apartment", "propertyTypeId": 10, "range": null, "data": [{"id": "650184", "price": {"value": null, "displayValue": "Price on Request", "unit": null, "deposit": null, "description": null}, "unitsAvailable": null, "areaConfig": [{"name": "Builtup Area", "areaInfo": {"value": 350, "unit": "sq.ft", "displayArea": "350.00"}}], "emi": null, "averagePrice": "Price on request", "floorPlan": null, "projectAttributes": null, "features": null, "additionalFields": [{"id": "bedroom", "value": "1", "label": "Bedroom"}]}]}]]